module.py
instra_together_client-0.0.3.dist-info/METADATA
instra_together_client-0.0.3.dist-info/WHEEL
instra_together_client-0.0.3.dist-info/top_level.txt
instra_together_client-0.0.3.dist-info/RECORD
